awesome_library/__init__.py
awesome_library/core.py
awesome_library_pypi-0.0.2.dist-info/licenses/LICENSE
awesome_library_pypi-0.0.2.dist-info/METADATA
awesome_library_pypi-0.0.2.dist-info/WHEEL
awesome_library_pypi-0.0.2.dist-info/top_level.txt
awesome_library_pypi-0.0.2.dist-info/RECORD
